[{
    "id": 1,
    "date": "07/10/2020",
    "punch_in": "8:04 AM",
    "punch_out": "5:47 PM",
    "break": 1,
    "overtime": 1
  }, {
    "id": 2,
    "date": "06/03/2021",
    "punch_in": "8:26 AM",
    "punch_out": "5:05 PM",
    "break": 1,
    "overtime": 1
  }, {
    "id": 3,
    "date": "29/04/2021",
    "punch_in": "8:44 AM",
    "punch_out": "5:26 PM",
    "break": 1,
    "overtime": 1
  }, {
    "id": 4,
    "date": "26/05/2020",
    "punch_in": "8:36 AM",
    "punch_out": "5:09 PM",
    "break": 1,
    "overtime": 1
  }, {
    "id": 5,
    "date": "27/11/2020",
    "punch_in": "8:37 AM",
    "punch_out": "5:22 PM",
    "break": 1,
    "overtime": 2
  }, {
    "id": 6,
    "date": "08/02/2021",
    "punch_in": "8:30 AM",
    "punch_out": "5:09 PM",
    "break": 1,
    "overtime": 2
  }, {
    "id": 7,
    "date": "15/10/2020",
    "punch_in": "8:05 AM",
    "punch_out": "5:17 PM",
    "break": 1,
    "overtime": 1
  }, {
    "id": 8,
    "date": "21/01/2021",
    "punch_in": "8:01 AM",
    "punch_out": "5:03 PM",
    "break": 1,
    "overtime": 2
  }, {
    "id": 9,
    "date": "26/04/2020",
    "punch_in": "8:12 AM",
    "punch_out": "5:11 PM",
    "break": 1,
    "overtime": 1
  }, {
    "id": 10,
    "date": "02/03/2021",
    "punch_in": "8:33 AM",
    "punch_out": "5:48 PM",
    "break": 1,
    "overtime": 1
  }, {
    "id": 11,
    "date": "14/09/2020",
    "punch_in": "8:36 AM",
    "punch_out": "5:36 PM",
    "break": 1,
    "overtime": 2
  }, {
    "id": 12,
    "date": "14/03/2021",
    "punch_in": "8:07 AM",
    "punch_out": "5:33 PM",
    "break": 1,
    "overtime": 1
  }, {
    "id": 13,
    "date": "25/10/2020",
    "punch_in": "8:39 AM",
    "punch_out": "5:17 PM",
    "break": 1,
    "overtime": 3
  }, {
    "id": 14,
    "date": "22/01/2021",
    "punch_in": "8:56 AM",
    "punch_out": "5:59 PM",
    "break": 1,
    "overtime": 2
  }, {
    "id": 15,
    "date": "15/06/2020",
    "punch_in": "8:26 AM",
    "punch_out": "5:59 PM",
    "break": 1,
    "overtime": 1
  }, {
    "id": 16,
    "date": "23/09/2020",
    "punch_in": "8:12 AM",
    "punch_out": "5:44 PM",
    "break": 1,
    "overtime": 1
  }, {
    "id": 17,
    "date": "27/05/2020",
    "punch_in": "8:44 AM",
    "punch_out": "5:08 PM",
    "break": 1,
    "overtime": 2
  }, {
    "id": 18,
    "date": "17/04/2021",
    "punch_in": "8:02 AM",
    "punch_out": "5:42 PM",
    "break": 1,
    "overtime": 2
  }, {
    "id": 19,
    "date": "21/04/2020",
    "punch_in": "8:55 AM",
    "punch_out": "5:14 PM",
    "break": 1,
    "overtime": 2
  }, {
    "id": 20,
    "date": "25/10/2020",
    "punch_in": "8:55 AM",
    "punch_out": "5:37 PM",
    "break": 1,
    "overtime": 2
  }, {
    "id": 21,
    "date": "30/07/2020",
    "punch_in": "8:20 AM",
    "punch_out": "5:00 PM",
    "break": 1,
    "overtime": 1
  }, {
    "id": 22,
    "date": "13/10/2020",
    "punch_in": "8:29 AM",
    "punch_out": "5:12 PM",
    "break": 1,
    "overtime": 2
  }, {
    "id": 23,
    "date": "29/06/2020",
    "punch_in": "8:09 AM",
    "punch_out": "5:52 PM",
    "break": 1,
    "overtime": 2
  }, {
    "id": 24,
    "date": "21/05/2020",
    "punch_in": "8:58 AM",
    "punch_out": "5:02 PM",
    "break": 1,
    "overtime": 1
  }, {
    "id": 25,
    "date": "28/10/2020",
    "punch_in": "8:30 AM",
    "punch_out": "5:40 PM",
    "break": 1,
    "overtime": 3
  }, {
    "id": 26,
    "date": "01/07/2020",
    "punch_in": "8:19 AM",
    "punch_out": "5:36 PM",
    "break": 1,
    "overtime": 1
  }, {
    "id": 27,
    "date": "01/06/2020",
    "punch_in": "8:51 AM",
    "punch_out": "5:10 PM",
    "break": 1,
    "overtime": 2
  }, {
    "id": 28,
    "date": "03/04/2021",
    "punch_in": "8:18 AM",
    "punch_out": "5:57 PM",
    "break": 1,
    "overtime": 3
  }, {
    "id": 29,
    "date": "18/09/2020",
    "punch_in": "8:05 AM",
    "punch_out": "5:16 PM",
    "break": 1,
    "overtime": 1
  }, {
    "id": 30,
    "date": "06/06/2020",
    "punch_in": "8:54 AM",
    "punch_out": "5:25 PM",
    "break": 1,
    "overtime": 2
  }]